cs/app/portfwd.py
cs.app.portfwd-20221228.dist-info/METADATA
cs.app.portfwd-20221228.dist-info/WHEEL
cs.app.portfwd-20221228.dist-info/entry_points.txt
cs.app.portfwd-20221228.dist-info/top_level.txt
cs.app.portfwd-20221228.dist-info/RECORD
